{
  "schema_version": "1",
  "id": "audit-011-stage-1-finalization",
  "plan_id": "plan-011-stage-1-finalization",
  "auditor": "independent-auditor",
  "scope": "检查阶段 1 治理收尾是否完成：历史 .abh JSON schema_version 迁移、doctor schema_version 门禁、CI editable install 路径、roadmap/task-board 状态同步",
  "status": "complete",
  "result": "pass",
  "rationale": "阶段 1 治理收尾的四个 exit criteria 全部满足：所有 .abh JSON 文件均包含 schema_version: '1'；abh doctor 能对 plans/audits/memory/drift 检查缺失 schema_version 并有测试覆盖；CI workflow 在 unittest 前加入 python3 -m pip install -e .；roadmap 明确标记阶段 1 已完成并将下一计划指向阶段 2 的 verify runner。Non-goals 未被执行。审计中的低风险 finding 已处理：DriftFinding 不再单独输出 schema_version，doctor 注释说明 verifications 暂不纳入 JSON/Markdown 一致性检查。",
  "evidence": [
    "docs/plans/plan-011-stage-1-finalization.md",
    "docs/development-roadmap.md",
    "docs/task-board.md",
    ".github/workflows/ci.yml",
    "abh/core.py",
    "abh/models.py",
    "tests/test_cli.py",
    ".abh/plans/plan-001-sprint-1-foundation.json",
    ".abh/audits/audit-001-sprint-1-foundation.json",
    ".abh/memory/mem-doc-sync-001.json",
    ".abh/drift/drift-test-007.json"
  ],
  "findings": [
    {
      "severity": "Low",
      "finding": "DriftFinding 与 AuditFinding 的 schema_version 行为曾不一致",
      "evidence": "abh/models.py",
      "recommendation": "已统一为嵌套 finding 不输出 schema_version"
    },
    {
      "severity": "Low",
      "finding": "doctor 不检查 verifications 目录",
      "evidence": "abh/core.py DOCTOR_OBJECTS",
      "recommendation": "已补充注释说明 verification runs 当前是 JSON-only execution evidence"
    },
    {
      "severity": "Info",
      "finding": "plan-011 在审计记录前仍为 ready",
      "evidence": ".abh/plans/plan-011-stage-1-finalization.json",
      "recommendation": "审计记录后执行 close 关闭计划"
    }
  ],
  "follow_ups": [
    "启动阶段 2 的 verify runner 计划",
    "后续如 verifications 需要 Markdown 文档，再扩展 doctor 覆盖该目录"
  ],
  "created_at": "2026-05-23T14:13:41.970637+00:00",
  "updated_at": "2026-05-23T14:13:56.826720+00:00",
  "doc_path": "/Users/cc/ai/harness-before/docs/audits/audit-011-stage-1-finalization.md"
}
